.git/COMMIT_EDITMSG
.git/FETCH_HEAD
.git/HEAD
.git/ORIG_HEAD
.git/config
.git/description
.git/hooks/applypatch-msg.sample
.git/hooks/commit-msg.sample
.git/hooks/fsmonitor-watchman.sample
.git/hooks/post-update.sample
.git/hooks/pre-applypatch.sample
.git/hooks/pre-commit.sample
.git/hooks/pre-merge-commit.sample
.git/hooks/pre-push.sample
.git/hooks/pre-rebase.sample
.git/hooks/pre-receive.sample
.git/hooks/prepare-commit-msg.sample
.git/hooks/push-to-checkout.sample
.git/hooks/sendemail-validate.sample
.git/hooks/update.sample
.git/index
.git/info/exclude
.git/logs/HEAD
.git/logs/refs/heads/iyue
.git/logs/refs/remotes/origin/HEAD
.git/logs/refs/remotes/origin/iyue
.git/objects/10/b5745d73a901581465c9246017b4affbc746f1
.git/objects/11/7ef3a7483715cced54a69f7b87e450884a2778
.git/objects/13/b28fb11edc16a49da04a079dc6c5313f069d5f
.git/objects/15/6115a51a86362b6261f11b69fdd257809a1b22
.git/objects/16/d893e92dc27aa063a50c1d5bf292e48d33d8be
.git/objects/1c/1d662f8fc133d612a7c9c6a4016a58f82d0e58
.git/objects/38/80810f211b550a0cc8b29fbec8c8934af4f608
.git/objects/3a/5ff8f362a5ba39d7e81128768c37ca23aad996
.git/objects/3b/9d78ccafcadeb7bdb687df2dea95a19b4ee019
.git/objects/3e/0e02b36834d32fd8ad74cc6da40dc8d86bea32
.git/objects/40/fc0bfa3b04d3177520d25a60d83e61318b3dbb
.git/objects/42/923313cbdf7c270a7fd21e962fd3cad85be547
.git/objects/44/17045d89498a9568b8f7ec9ff8c33ceffb6a2f
.git/objects/4f/1b426c7cf13e8430a2a9c2b264236af32c0173
.git/objects/4f/20812711cbaa6b29e187d5813fffecd32c4d89
.git/objects/4f/c1a50b60d2912fca0024868d17ef3a7bbf5f26
.git/objects/5e/d8732008107c39b266189765d5067a218c9223
.git/objects/63/330ea71c2681094e9a49520fa68d6111b67414
.git/objects/6e/ca5d6d1933680820c606f516d9cb1af6decd62
.git/objects/6f/8097bd9bfeaaa360e8bb0fccaa64038d11efd5
.git/objects/72/f5117cd6e970c0bd718f8f55cb90ab82bc007f
.git/objects/75/7391ccd4e8400285863d10a5d1693c12c2c8cf
.git/objects/7c/8eef1732e681e37009c1d12191f731bf3d9caa
.git/objects/8d/8e70d679e09f1206596fd154b65be674866dbc
reproto-0.2.4.dist-info/METADATA
reproto-0.2.4.dist-info/WHEEL
reproto-0.2.4.dist-info/entry_points.txt
reproto-0.2.4.dist-info/RECORD
