Metadata-Version: 2.3
Name: reproto
Version: 0.2.4
Summary: 一个强大的逆向工程工具, 能够从任何使用Google Protobuf Lite的Android应用中自动重构出完整的.proto文件结构.
License: Proprietary
Keywords: protobuf,reverse-engineering,android,jadx,proto
Author: iyue
Author-email: ys1231@126.com
Requires-Python: >=3.12,<4.0
Classifier: Development Status :: 4 - Beta
Classifier: Intended Audience :: Developers
Classifier: License :: Other/Proprietary License
Classifier: Programming Language :: Python :: 3
Classifier: Programming Language :: Python :: 3.12
Classifier: Programming Language :: Python :: 3.13
Classifier: Topic :: Software Development :: Code Generators
Classifier: Topic :: Software Development :: Disassemblers
Requires-Dist: loguru (>=0.7.3)
Requires-Dist: packaging (>=25.0,<26.0)
Requires-Dist: protobuf (>=6.31.1,<7.0.0)
Project-URL: Homepage, https://github.com/ys1231/reproto
Project-URL: Repository, https://github.com/ys1231/reproto.git
